deepcomparer/__init__.py
deepcomparer/deep_compare.py
deepcomparer-0.3.0.dist-info/LICENSE
deepcomparer-0.3.0.dist-info/METADATA
deepcomparer-0.3.0.dist-info/WHEEL
deepcomparer-0.3.0.dist-info/top_level.txt
deepcomparer-0.3.0.dist-info/RECORD
