Metadata-Version: 2.1
Name: deepcomparer
Version: 0.3.0
Summary: Deep compare python structures like dictionaries, lists and iterables.
Home-page: https://github.com/jparadadev/deepcomparer.py
Author: Javier Parada
Author-email: javierparadadev@gmail.com
License: MIT
Project-URL: Bug Tracker, https://github.com/jparadadev/deepcomparer.py/issues
Keywords: compare,dictionary,list,array,deep,find,structure,nested,data
Platform: any
Classifier: Programming Language :: Python :: 3.7
Classifier: Programming Language :: Python :: 3.8
Classifier: Programming Language :: Python :: 3.9
Classifier: Programming Language :: Python :: 3.10
Classifier: License :: OSI Approved :: MIT License
Classifier: Operating System :: OS Independent
Requires-Python: >=3.7
License-File: LICENSE
